plexrec/__init__.py
plexrec/__main__.py
plexrec/app.py
plexrec/config.py
plexrec/database.py
plexrec/media.py
plexrec/playlist.py
plexrec/similarity.py
plexrec/subtitle.py
plexrec/suggest.py
PlexRec-0.1.1.dist-info/LICENSE
PlexRec-0.1.1.dist-info/METADATA
PlexRec-0.1.1.dist-info/WHEEL
PlexRec-0.1.1.dist-info/top_level.txt
PlexRec-0.1.1.dist-info/RECORD
