Metadata-Version: 2.1
Name: PlexRec
Version: 0.1.1
Summary: Default template for PDM package
Author-email: TKDKid1000 <rhoneeiler@gmail.com>
License: MIT
Requires-Python: ==3.11.*
License-File: LICENSE
Requires-Dist: plexapi>=4.15.9
Requires-Dist: python-dotenv>=1.0.1
Requires-Dist: openai>=1.12.0
Requires-Dist: numpy>=1.26.4
Requires-Dist: scikit-learn>=1.4.0
Requires-Dist: matplotlib>=3.8.2
Requires-Dist: chromadb>=0.4.22
Requires-Dist: tqdm>=4.66.1
Requires-Dist: sentence-transformers>=2.3.1
Requires-Dist: pyyaml>=6.0.1
Requires-Dist: fastapi>=0.109.2
Requires-Dist: uvicorn>=0.27.1
Requires-Dist: jinja2>=3.1.3
Requires-Dist: m3u8>=4.0.0
Requires-Dist: requests-cache>=1.2.0
